CHANGES.txt
LICENSE.txt
MANIFEST.in
README.txt
setup.py
js/__init__.py
js.expect.egg-info/PKG-INFO
js.expect.egg-info/SOURCES.txt
js.expect.egg-info/dependency_links.txt
js.expect.egg-info/entry_points.txt
js.expect.egg-info/namespace_packages.txt
js.expect.egg-info/not-zip-safe
js.expect.egg-info/requires.txt
js.expect.egg-info/top_level.txt
js/expect/__init__.py
js/expect/test_expect.js.txt
js/expect/resources/index.js