Metadata-Version: 1.0
Name: js.expect
Version: 0.3.1
Summary: Fanstatic packaging of expect.js
Home-page: UNKNOWN
Author: Fanstatic Developers
Author-email: fanstatic@googlegroups.com
License: BSD
Platform: UNKNOWN
